pycom0com/__init__.py
pycom0com/_installer.py
pycom0com/core.py
pycom0com/bin/ReadMe.txt
pycom0com/bin/cncport.inf
pycom0com/bin/com0com.cat
pycom0com/bin/com0com.inf
pycom0com/bin/com0com.sys
pycom0com/bin/comport.inf
pycom0com/bin/setup.dll
pycom0com-1.0.3.dist-info/METADATA
pycom0com-1.0.3.dist-info/WHEEL
pycom0com-1.0.3.dist-info/entry_points.txt
pycom0com-1.0.3.dist-info/top_level.txt
pycom0com-1.0.3.dist-info/RECORD
