Metadata-Version: 2.1
Name: pycom0com
Version: 1.0.3
Summary: Python bindings for com0com virtual serial ports
Home-page: https://github.com/StableKite/pycom0com
Author: StableKite
Author-email: StableKite <stablekite@stablekite.com>
License: GPL-2.0
Project-URL: Homepage, https://github.com/StableKite/pycom0com
Keywords: com0com,serial,virtual ports
Classifier: Development Status :: 4 - Beta
Classifier: Intended Audience :: Developers
Classifier: License :: OSI Approved :: GNU General Public License v2 (GPLv2)
Classifier: Operating System :: Microsoft :: Windows
Classifier: Programming Language :: Python :: 3
Classifier: Programming Language :: Python :: 3.7
Classifier: Programming Language :: Python :: 3.8
Classifier: Programming Language :: Python :: 3.9
Classifier: Programming Language :: Python :: 3.10
Classifier: Programming Language :: Python :: 3.11
Classifier: Programming Language :: Python :: 3.12
Requires-Python: >=3.7
